README.md
setup.py
pyblinkpico/__init__.py
pyblinkpico/pyblinkpico.py
pyblinkpico.egg-info/PKG-INFO
pyblinkpico.egg-info/SOURCES.txt
pyblinkpico.egg-info/dependency_links.txt
pyblinkpico.egg-info/top_level.txt